[
    {
        "name": "SAILS Library Network",
        "slug": "sails",
        "url": "https://sails.ent.sirsi.net/client/en_US/default/",
        "action": "https://sails.ent.sirsi.net/client/en_US/default/search/results"
    },
    {
        "name": "Goodreads",
        "slug": "goodreads",
        "url": "https://www.goodreads.com/",
        "action": "https://www.goodreads.com/search"
    },
    {
        "name": "IndieBound",
        "slug": "indiebound",
        "url": "https://www.indiebound.org/",
        "action": "https://www.indiebound.org/search/book",
        "field": "keys"
    },
    {
        "name": "WorldCat",
        "slug": "worldcat",
        "url": "https://www.worldcat.org/",
        "action": "https://www.worldcat.org/search"
    }
]
