[
  {
    "name": "Book Stacks",
    "slug": "bookstacks",
    "url": "https://bookstacks.app/",
    "action": "https://bookstacks.app/search",
    "field": "q"
  },
  {
    "name": "Norwich Bookstore",
    "slug": "norwich",
    "url": "https://www.norwichbookstore.com/",
    "action": "https://www.norwichbookstore.com/browse/",
    "field": "qs"
  },
  {
    "name": "Kobo",
    "slug": "kobo",
    "url": "https://www.kobo.com/",
    "action": "https://www.kobo.com/us/en/search",
    "field": "query"
  },
  {
    "name": "Open Library",
    "slug": "openlibrary",
    "url": "https://openlibrary.org/",
    "action": "https://openlibrary.org/search",
    "field": "q"
  },
  {
    "name": "The StoryGraph",
    "slug": "storygraph",
    "url": "https://app.thestorygraph.com/",
    "action": "https://app.thestorygraph.com/browse",
    "field": "search_term"
  },
  {
    "name": "Strafford Library",
    "slug": "morrill",
    "url": "https://opac.libraryworld.com/opac/signin.php?libraryname=Morrill%20Memorial%20Library",
    "action": "https://opac.libraryworld.com/opac/signin.php?libraryname=Morrill%20Memorial%20Library",
    "field": "term",
    "method": "post"
  },
  {
    "name": "Goodreads",
    "slug": "goodreads",
    "url": "https://www.goodreads.com/",
    "action": "https://www.goodreads.com/search"
  },
  {
    "name": "Bookshop",
    "slug": "bookshop",
    "url": "https://bookshop.org/",
    "action": "https://bookshop.org/books",
    "field": "keywords"
  },
  {
    "name": "WorldCat",
    "slug": "worldcat",
    "url": "https://www.worldcat.org/",
    "action": "https://www.worldcat.org/search?fq=x0%3Abook&qt=advanced&dblist=638#x0%253Abook-%2C%2528x0%253Abook%2Bx4%253Aprintbook%2529format"
  },
  {
    "name": "Wikipedia",
    "slug": "wikipedia",
    "url": "https://en.wikipedia.org/",
    "action": "https://en.wikipedia.org/w/index.php?search",
    "field": "search"
  }
]
